spydcmtk/ParaViewGlance.html
spydcmtk/__init__.py
spydcmtk/dcmTK.py
spydcmtk/dcmTools.py
spydcmtk/dcmVTKTK.py
spydcmtk/spydcm.py
spydcmtk/spydcm_config.py
spydcmtk/spydcmtk.conf
spydcmtk/tests/__init__.py
spydcmtk/tests/context.py
spydcmtk/tests/run_tests.py
spydcmtk/tests/test_3d_dicom.py
spydcmtk-1.2.18.dist-info/METADATA
spydcmtk-1.2.18.dist-info/WHEEL
spydcmtk-1.2.18.dist-info/entry_points.txt
spydcmtk-1.2.18.dist-info/licenses/LICENSE
spydcmtk-1.2.18.dist-info/RECORD
