Metadata-Version: 2.4
Name: spydcmtk
Version: 1.2.18
Summary: Simple python dicom toolkit.
Project-URL: Homepage, https://github.com/fraser29/spydcmtk
Author-email: "Fraser M. Callaghan" <callaghan.fm@gmail.com>
License: MIT
License-File: LICENSE
Keywords: ct,dicom,imaging,medical,mri
Classifier: Development Status :: 5 - Production/Stable
Classifier: Intended Audience :: Developers
Classifier: License :: OSI Approved :: MIT License
Classifier: Operating System :: OS Independent
Classifier: Programming Language :: Python
Classifier: Programming Language :: Python :: 3
Classifier: Programming Language :: Python :: 3.9
Classifier: Programming Language :: Python :: 3.10
Classifier: Programming Language :: Python :: 3.11
Classifier: Topic :: Scientific/Engineering :: Image Processing
Requires-Python: >=3.9.0
Requires-Dist: highdicom==0.25.0
Requires-Dist: matplotlib
Requires-Dist: ngawari>=0.1.11
Requires-Dist: numpy>=2.2.3
Requires-Dist: pydicom>=3.0.1
Requires-Dist: python-gdcm
Requires-Dist: tqdm>=4.66.1
Requires-Dist: vtk>=9.3.0
